{
  "update_time": "2026-06-16 00:14:10",
  "stocks": {
    "爱乐达": {
      "total_trades": 2,
      "completed_trades": 1,
      "win_trades": 1,
      "win_rate": 100.0,
      "total_return": 9.45,
      "avg_return": 9.45,
      "max_profit": 9.45,
      "max_loss": 9.45
    },
    "川润股份": {
      "total_trades": 2,
      "completed_trades": 0,
      "win_trades": 0,
      "win_rate": null,
      "total_return": 0,
      "avg_return": null,
      "max_profit": null,
      "max_loss": null
    },
    "高澜股份": {
      "total_trades": 1,
      "completed_trades": 0,
      "win_trades": 0,
      "win_rate": null,
      "total_return": 0,
      "avg_return": null,
      "max_profit": null,
      "max_loss": null
    }
  }
}